{
  "src/content/docs/docs/quick-start.md": {
    "author": {
      "name": "Tommy Lundy",
      "email": "tommerty@doras.to",
      "commits": 4,
      "github": "tommerty",
      "avatar_url": "https://avatars.githubusercontent.com/u/86270372?v=4",
      "profile_url": "https://github.com/tommerty"
    },
    "contributors": []
  },
  "src/content/docs/docs/index.md": {
    "author": {
      "name": "Tommy Lundy",
      "email": "tommerty@doras.to",
      "commits": 5,
      "github": "tommerty",
      "avatar_url": "https://avatars.githubusercontent.com/u/86270372?v=4",
      "profile_url": "https://github.com/tommerty"
    },
    "contributors": []
  },
  "src/content/docs/docs/404.md": {
    "author": {
      "name": "Tommy Lundy",
      "email": "tommerty@doras.to",
      "commits": 1,
      "github": "tommerty",
      "avatar_url": "https://avatars.githubusercontent.com/u/86270372?v=4",
      "profile_url": "https://github.com/tommerty"
    },
    "contributors": []
  },
  "src/content/docs/docs/visibility/public-pages.md": {
    "author": {
      "name": "Tommy Lundy",
      "email": "tommerty@doras.to",
      "commits": 2,
      "github": "tommerty",
      "avatar_url": "https://avatars.githubusercontent.com/u/86270372?v=4",
      "profile_url": "https://github.com/tommerty"
    },
    "contributors": []
  },
  "src/content/docs/docs/visibility/overview.md": {
    "author": {
      "name": "Tommy Lundy",
      "email": "tommerty@doras.to",
      "commits": 1,
      "github": "tommerty",
      "avatar_url": "https://avatars.githubusercontent.com/u/86270372?v=4",
      "profile_url": "https://github.com/tommerty"
    },
    "contributors": []
  },
  "src/content/docs/docs/tasks/templates.md": {
    "author": {
      "name": "Tommy Lundy",
      "email": "tommerty@doras.to",
      "commits": 1,
      "github": "tommerty",
      "avatar_url": "https://avatars.githubusercontent.com/u/86270372?v=4",
      "profile_url": "https://github.com/tommerty"
    },
    "contributors": []
  },
  "src/content/docs/docs/tasks/tasks.md": {
    "author": {
      "name": "Tommy Lundy",
      "email": "tommerty@doras.to",
      "commits": 1,
      "github": "tommerty",
      "avatar_url": "https://avatars.githubusercontent.com/u/86270372?v=4",
      "profile_url": "https://github.com/tommerty"
    },
    "contributors": []
  },
  "src/content/docs/docs/tasks/task-relations.md": {
    "author": {
      "name": "Tommy Lundy",
      "email": "tommerty@doras.to",
      "commits": 1,
      "github": "tommerty",
      "avatar_url": "https://avatars.githubusercontent.com/u/86270372?v=4",
      "profile_url": "https://github.com/tommerty"
    },
    "contributors": []
  },
  "src/content/docs/docs/tasks/subtasks.md": {
    "author": {
      "name": "Tommy Lundy",
      "email": "tommerty@doras.to",
      "commits": 1,
      "github": "tommerty",
      "avatar_url": "https://avatars.githubusercontent.com/u/86270372?v=4",
      "profile_url": "https://github.com/tommerty"
    },
    "contributors": []
  },
  "src/content/docs/docs/self-hosting/get-started.md": {
    "author": {
      "name": "Tommy Lundy",
      "email": "tommerty@doras.to",
      "commits": 2,
      "github": "tommerty",
      "avatar_url": "https://avatars.githubusercontent.com/u/86270372?v=4",
      "profile_url": "https://github.com/tommerty"
    },
    "contributors": []
  },
  "src/content/docs/docs/self-hosting/editions.md": {
    "author": {
      "name": "Tommy Lundy",
      "email": "tommerty@doras.to",
      "commits": 1,
      "github": "tommerty",
      "avatar_url": "https://avatars.githubusercontent.com/u/86270372?v=4",
      "profile_url": "https://github.com/tommerty"
    },
    "contributors": []
  },
  "src/content/docs/docs/self-hosting/authentication.md": {
    "author": {
      "name": "Tommy Lundy",
      "email": "tommerty@doras.to",
      "commits": 1,
      "github": "tommerty",
      "avatar_url": "https://avatars.githubusercontent.com/u/86270372?v=4",
      "profile_url": "https://github.com/tommerty"
    },
    "contributors": []
  },
  "src/content/docs/docs/organize/views.md": {
    "author": {
      "name": "Tommy Lundy",
      "email": "tommerty@doras.to",
      "commits": 2,
      "github": "tommerty",
      "avatar_url": "https://avatars.githubusercontent.com/u/86270372?v=4",
      "profile_url": "https://github.com/tommerty"
    },
    "contributors": []
  },
  "src/content/docs/docs/organize/releases.md": {
    "author": {
      "name": "Tommy Lundy",
      "email": "tommerty@doras.to",
      "commits": 3,
      "github": "tommerty",
      "avatar_url": "https://avatars.githubusercontent.com/u/86270372?v=4",
      "profile_url": "https://github.com/tommerty"
    },
    "contributors": []
  },
  "src/content/docs/docs/organize/labels.md": {
    "author": {
      "name": "Tommy Lundy",
      "email": "tommerty@doras.to",
      "commits": 1,
      "github": "tommerty",
      "avatar_url": "https://avatars.githubusercontent.com/u/86270372?v=4",
      "profile_url": "https://github.com/tommerty"
    },
    "contributors": []
  },
  "src/content/docs/docs/organize/categories.md": {
    "author": {
      "name": "Tommy Lundy",
      "email": "tommerty@doras.to",
      "commits": 1,
      "github": "tommerty",
      "avatar_url": "https://avatars.githubusercontent.com/u/86270372?v=4",
      "profile_url": "https://github.com/tommerty"
    },
    "contributors": []
  },
  "src/content/docs/docs/organizations/preferences.md": {
    "author": {
      "name": "Tommy Lundy",
      "email": "tommerty@doras.to",
      "commits": 1,
      "github": "tommerty",
      "avatar_url": "https://avatars.githubusercontent.com/u/86270372?v=4",
      "profile_url": "https://github.com/tommerty"
    },
    "contributors": []
  },
  "src/content/docs/docs/organizations/overview.md": {
    "author": {
      "name": "Tommy Lundy",
      "email": "tommerty@doras.to",
      "commits": 2,
      "github": "tommerty",
      "avatar_url": "https://avatars.githubusercontent.com/u/86270372?v=4",
      "profile_url": "https://github.com/tommerty"
    },
    "contributors": []
  },
  "src/content/docs/docs/organizations/members-and-teams.md": {
    "author": {
      "name": "Tommy Lundy",
      "email": "tommerty@doras.to",
      "commits": 2,
      "github": "tommerty",
      "avatar_url": "https://avatars.githubusercontent.com/u/86270372?v=4",
      "profile_url": "https://github.com/tommerty"
    },
    "contributors": []
  },
  "src/content/docs/docs/organizations/danger-zone.md": {
    "author": {
      "name": "Tommy Lundy",
      "email": "tommerty@doras.to",
      "commits": 1,
      "github": "tommerty",
      "avatar_url": "https://avatars.githubusercontent.com/u/86270372?v=4",
      "profile_url": "https://github.com/tommerty"
    },
    "contributors": []
  },
  "src/content/docs/docs/organizations/billing.md": {
    "author": {
      "name": "Tommy Lundy",
      "email": "tommerty@doras.to",
      "commits": 1,
      "github": "tommerty",
      "avatar_url": "https://avatars.githubusercontent.com/u/86270372?v=4",
      "profile_url": "https://github.com/tommerty"
    },
    "contributors": []
  },
  "src/content/docs/docs/knowledge-base/index.md": {
    "author": {
      "name": "Tommy Lundy",
      "email": "tommerty@doras.to",
      "commits": 2,
      "github": "tommerty",
      "avatar_url": "https://avatars.githubusercontent.com/u/86270372?v=4",
      "profile_url": "https://github.com/tommerty"
    },
    "contributors": []
  },
  "src/content/docs/docs/knowledge-base/faq.md": {
    "author": {
      "name": "Tommy Lundy",
      "email": "tommerty@doras.to",
      "commits": 4,
      "github": "tommerty",
      "avatar_url": "https://avatars.githubusercontent.com/u/86270372?v=4",
      "profile_url": "https://github.com/tommerty"
    },
    "contributors": []
  },
  "src/content/docs/docs/integrations/github.md": {
    "author": {
      "name": "Tommy Lundy",
      "email": "tommerty@doras.to",
      "commits": 2,
      "github": "tommerty",
      "avatar_url": "https://avatars.githubusercontent.com/u/86270372?v=4",
      "profile_url": "https://github.com/tommerty"
    },
    "contributors": []
  },
  "src/content/docs/docs/contributing/schema-types.mdx": {
    "author": {
      "name": "Tommy Lundy",
      "email": "tommerty@doras.to",
      "commits": 3,
      "github": "tommerty",
      "avatar_url": "https://avatars.githubusercontent.com/u/86270372?v=4",
      "profile_url": "https://github.com/tommerty"
    },
    "contributors": []
  },
  "src/content/docs/docs/contributing/local-development.mdx": {
    "author": {
      "name": "Tommy Lundy",
      "email": "tommerty@doras.to",
      "commits": 1,
      "github": "tommerty",
      "avatar_url": "https://avatars.githubusercontent.com/u/86270372?v=4",
      "profile_url": "https://github.com/tommerty"
    },
    "contributors": []
  },
  "src/content/docs/docs/contributing/edition-system.md": {
    "author": {
      "name": "Tommy Lundy",
      "email": "tommerty@doras.to",
      "commits": 2,
      "github": "tommerty",
      "avatar_url": "https://avatars.githubusercontent.com/u/86270372?v=4",
      "profile_url": "https://github.com/tommerty"
    },
    "contributors": []
  },
  "src/content/docs/docs/contributing/documentation.md": {
    "author": {
      "name": "Tommy Lundy",
      "email": "tommerty@doras.to",
      "commits": 6,
      "github": "tommerty",
      "avatar_url": "https://avatars.githubusercontent.com/u/86270372?v=4",
      "profile_url": "https://github.com/tommerty"
    },
    "contributors": []
  },
  "src/content/docs/docs/contributing/database.md": {
    "author": {
      "name": "Tommy Lundy",
      "email": "tommerty@doras.to",
      "commits": 1,
      "github": "tommerty",
      "avatar_url": "https://avatars.githubusercontent.com/u/86270372?v=4",
      "profile_url": "https://github.com/tommerty"
    },
    "contributors": []
  },
  "src/content/docs/docs/contributing/architecture.md": {
    "author": {
      "name": "Tommy Lundy",
      "email": "tommerty@doras.to",
      "commits": 3,
      "github": "tommerty",
      "avatar_url": "https://avatars.githubusercontent.com/u/86270372?v=4",
      "profile_url": "https://github.com/tommerty"
    },
    "contributors": [
      {
        "name": "Trent",
        "email": "64388078+trent-001@users.noreply.github.com",
        "commits": 2,
        "github": "trent-001",
        "avatar_url": "https://avatars.githubusercontent.com/u/64388078?v=4",
        "profile_url": "https://github.com/trent-001"
      }
    ]
  },
  "src/content/docs/docs/contributing/adding-features.md": {
    "author": {
      "name": "Tommy Lundy",
      "email": "tommerty@doras.to",
      "commits": 3,
      "github": "tommerty",
      "avatar_url": "https://avatars.githubusercontent.com/u/86270372?v=4",
      "profile_url": "https://github.com/tommerty"
    },
    "contributors": [
      {
        "name": "Trent",
        "email": "64388078+trent-001@users.noreply.github.com",
        "commits": 1,
        "github": "trent-001",
        "avatar_url": "https://avatars.githubusercontent.com/u/64388078?v=4",
        "profile_url": "https://github.com/trent-001"
      }
    ]
  },
  "src/content/docs/docs/contributing/Guidelines/testing.md": {
    "author": {
      "name": "Tommy Lundy",
      "email": "tommerty@doras.to",
      "commits": 2,
      "github": "tommerty",
      "avatar_url": "https://avatars.githubusercontent.com/u/86270372?v=4",
      "profile_url": "https://github.com/tommerty"
    },
    "contributors": []
  },
  "src/content/docs/docs/contributing/Guidelines/pull-requests.md": {
    "author": {
      "name": "Tommy Lundy",
      "email": "tommerty@doras.to",
      "commits": 2,
      "github": "tommerty",
      "avatar_url": "https://avatars.githubusercontent.com/u/86270372?v=4",
      "profile_url": "https://github.com/tommerty"
    },
    "contributors": []
  },
  "src/content/docs/docs/contributing/Guidelines/code-style.md": {
    "author": {
      "name": "Tommy Lundy",
      "email": "tommerty@doras.to",
      "commits": 4,
      "github": "tommerty",
      "avatar_url": "https://avatars.githubusercontent.com/u/86270372?v=4",
      "profile_url": "https://github.com/tommerty"
    },
    "contributors": [
      {
        "name": "Trent",
        "email": "64388078+trent-001@users.noreply.github.com",
        "commits": 1,
        "github": "trent-001",
        "avatar_url": "https://avatars.githubusercontent.com/u/64388078?v=4",
        "profile_url": "https://github.com/trent-001"
      }
    ]
  },
  "src/content/docs/docs/api/sdk.mdx": {
    "author": {
      "name": "Tommy Lundy",
      "email": "tommerty@doras.to",
      "commits": 2,
      "github": "tommerty",
      "avatar_url": "https://avatars.githubusercontent.com/u/86270372?v=4",
      "profile_url": "https://github.com/tommerty"
    },
    "contributors": [
      {
        "name": "trent-001",
        "email": "trent@doras.to",
        "commits": 2,
        "github": "trent-001",
        "avatar_url": "https://avatars.githubusercontent.com/u/64388078?v=4",
        "profile_url": "https://github.com/trent-001"
      }
    ]
  },
  "src/content/docs/docs/api/reference-v1.mdx": {
    "author": {
      "name": "Tommy Lundy",
      "email": "tommerty@doras.to",
      "commits": 3,
      "github": "tommerty",
      "avatar_url": "https://avatars.githubusercontent.com/u/86270372?v=4",
      "profile_url": "https://github.com/tommerty"
    },
    "contributors": [
      {
        "name": "trent-001",
        "email": "trent@doras.to",
        "commits": 2,
        "github": "trent-001",
        "avatar_url": "https://avatars.githubusercontent.com/u/64388078?v=4",
        "profile_url": "https://github.com/trent-001"
      }
    ]
  },
  "src/content/docs/docs/api/overview.md": {
    "author": {
      "name": "Tommy Lundy",
      "email": "tommerty@doras.to",
      "commits": 2,
      "github": "tommerty",
      "avatar_url": "https://avatars.githubusercontent.com/u/86270372?v=4",
      "profile_url": "https://github.com/tommerty"
    },
    "contributors": []
  },
  "src/content/docs/docs/account/security.md": {
    "author": {
      "name": "Tommy Lundy",
      "email": "tommerty@doras.to",
      "commits": 1,
      "github": "tommerty",
      "avatar_url": "https://avatars.githubusercontent.com/u/86270372?v=4",
      "profile_url": "https://github.com/tommerty"
    },
    "contributors": []
  },
  "src/content/docs/docs/account/notifications.md": {
    "author": {
      "name": "Tommy Lundy",
      "email": "tommerty@doras.to",
      "commits": 2,
      "github": "tommerty",
      "avatar_url": "https://avatars.githubusercontent.com/u/86270372?v=4",
      "profile_url": "https://github.com/tommerty"
    },
    "contributors": []
  },
  "src/content/docs/docs/account/my-tasks.md": {
    "author": {
      "name": "Tommy Lundy",
      "email": "tommerty@doras.to",
      "commits": 1,
      "github": "tommerty",
      "avatar_url": "https://avatars.githubusercontent.com/u/86270372?v=4",
      "profile_url": "https://github.com/tommerty"
    },
    "contributors": []
  },
  "src/content/docs/docs/account/account-settings.md": {
    "author": {
      "name": "Tommy Lundy",
      "email": "tommerty@doras.to",
      "commits": 2,
      "github": "tommerty",
      "avatar_url": "https://avatars.githubusercontent.com/u/86270372?v=4",
      "profile_url": "https://github.com/tommerty"
    },
    "contributors": []
  }
}